amxtelnet/__init__.py
amxtelnet-1.3.3.dist-info/LICENSE
amxtelnet-1.3.3.dist-info/METADATA
amxtelnet-1.3.3.dist-info/WHEEL
amxtelnet-1.3.3.dist-info/top_level.txt
amxtelnet-1.3.3.dist-info/RECORD
