Metadata-Version: 2.1
Name: amxtelnet
Version: 1.3.3
Summary: xlsx to amx dict list
Home-page: https://github.com/logantv/amxtelnet
Author: Logan Vaughn
License: UNKNOWN
Project-URL: Bug Tracker, https://github.com/logantv/amxtelnet/issues
Platform: UNKNOWN
Classifier: Programming Language :: Python :: 3
Classifier: License :: OSI Approved :: MIT License
Classifier: Operating System :: OS Independent
Requires-Python: >=3.6
License-File: LICENSE
